{"header":{"version":"1.0"},"dataSets":[{"id":"a171I0000011yBvQAI","name":"SBQQ 210 VEID Import Format Data Set","sobjectName":"sbqq__importformat__c","replicateOwner":false,"replicateRecordType":false,"createMissing":true,"syncPicklistValues":true,"setAuditFields":false,"ignoreNamespace":false,"ignoreRelationshipConstraints":false,"active":true,"root":true,"allFields":true,"overrideRootSettings":false,"useLocalSchema":true,"customUpsertRecordHandling":"Virtual External ID","originConnection":{"name":"PROD - Salesforce Hitech ver 210.15.7"},"dataSetFields":[],"relationships":[{"id":"a1G1I000000NUxkUAG","name":"SBQQ__ImportFormat__c","childDataSetId":"a171I0000011yBwQAI","parentDataSetId":"a171I0000011yBvQAI","isEnforceStrictQueryFilter":false,"isParentSelected":false,"isChildSelected":true}]},{"id":"a171I0000011yBwQAI","name":"Import Column","sobjectName":"sbqq__importcolumn__c","replicateOwner":false,"replicateRecordType":false,"createMissing":true,"syncPicklistValues":true,"setAuditFields":false,"ignoreNamespace":false,"ignoreRelationshipConstraints":false,"active":true,"root":false,"allFields":true,"overrideRootSettings":false,"useLocalSchema":false,"customUpsertRecordHandling":"Virtual External ID","dataSetFields":[],"relationships":[]}]}