{"header":{"version":"1.0"},"dataSets":[{"id":"a011D000000Oa2fQAC","name":"VEID - DIR - SBQQ Product Data Set(Updated)","sobjectName":"product2","replicateOwner":false,"replicateRecordType":false,"createMissing":true,"syncPicklistValues":true,"setAuditFields":false,"ignoreNamespace":false,"ignoreRelationshipConstraints":false,"active":true,"root":true,"allFields":true,"overrideRootSettings":false,"useLocalSchema":true,"customUpsertRecordHandling":"Virtual External ID","dataSetFields":[],"relationships":[{"id":"a0O1D0000007OSmUAM","name":"SBQQ__Product__c","childDataSetId":"a011D000000Oa31QAC","parentDataSetId":"a011D000000Oa2fQAC","isEnforceStrictQueryFilter":false,"isParentSelected":false,"isChildSelected":true},{"id":"a0O1D0000007OSSUA2","name":"SBQQ__Product__c","childDataSetId":"a011D000000Oa2gQAC","parentDataSetId":"a011D000000Oa2fQAC","isEnforceStrictQueryFilter":false,"isParentSelected":false,"isChildSelected":true},{"id":"a0O1D0000007OSgUAM","name":"SBQQ__ConfiguredSKU__c","childDataSetId":"a011D000000Oa2nQAC","parentDataSetId":"a011D000000Oa2fQAC","isEnforceStrictQueryFilter":false,"isParentSelected":false,"isChildSelected":true},{"id":"a0O1D0000007OSfUAM","name":"SBQQ__ConfiguredSKU__c","childDataSetId":"a011D000000Oa2mQAC","parentDataSetId":"a011D000000Oa2fQAC","isEnforceStrictQueryFilter":false,"isParentSelected":false,"isChildSelected":true},{"id":"a0O1D0000007OSeUAM","name":"SBQQ__Product__c","childDataSetId":"a011D000000Oa2oQAC","parentDataSetId":"a011D000000Oa2fQAC","isEnforceStrictQueryFilter":false,"isParentSelected":false,"isChildSelected":true},{"id":"a0O1D0000007OSdUAM","name":"SBQQ__Product__c","childDataSetId":"a011D000000Oa2zQAC","parentDataSetId":"a011D000000Oa2fQAC","isEnforceStrictQueryFilter":false,"isParentSelected":false,"isChildSelected":true},{"id":"a0O1D0000007OScUAM","name":"SBQQ__ConfiguredSKU__c","childDataSetId":"a011D000000Oa2qQAC","parentDataSetId":"a011D000000Oa2fQAC","isEnforceStrictQueryFilter":false,"isParentSelected":false,"isChildSelected":true},{"id":"a0O1D0000007OSbUAM","name":"SBQQ__Product__c","childDataSetId":"a011D000000Oa2rQAC","parentDataSetId":"a011D000000Oa2fQAC","isEnforceStrictQueryFilter":false,"isParentSelected":false,"isChildSelected":true},{"id":"a0O1D0000007OSaUAM","name":"SBQQ__Product__c","childDataSetId":"a011D000000Oa2pQAC","parentDataSetId":"a011D000000Oa2fQAC","isEnforceStrictQueryFilter":false,"isParentSelected":false,"isChildSelected":true},{"id":"a0O1D0000007OSZUA2","name":"SBQQ__UpgradeProduct__c","childDataSetId":"a011D000000Oa30QAC","parentDataSetId":"a011D000000Oa2fQAC","isEnforceStrictQueryFilter":false,"isParentSelected":false,"isChildSelected":true},{"id":"a0O1D0000007OSYUA2","name":"SBQQ__SourceProduct__c","childDataSetId":"a011D000000Oa30QAC","parentDataSetId":"a011D000000Oa2fQAC","isEnforceStrictQueryFilter":false,"isParentSelected":false,"isChildSelected":true},{"id":"a0O1D0000007OSXUA2","name":"SBQQ__Product__c","childDataSetId":"a011D000000Oa2wQAC","parentDataSetId":"a011D000000Oa2fQAC","isEnforceStrictQueryFilter":false,"isParentSelected":false,"isChildSelected":true},{"id":"a0O1D0000007OSWUA2","name":"SBQQ__Product__c","childDataSetId":"a011D000000Oa2lQAC","parentDataSetId":"a011D000000Oa2fQAC","isEnforceStrictQueryFilter":false,"isParentSelected":false,"isChildSelected":true},{"id":"a0O1D0000007OSVUA2","name":"SBQQ__Product__c","childDataSetId":"a011D000000Oa2jQAC","parentDataSetId":"a011D000000Oa2fQAC","isEnforceStrictQueryFilter":false,"isParentSelected":false,"isChildSelected":true},{"id":"a0O1D0000007OSUUA2","name":"SBQQ__OptionalSKU__c","childDataSetId":"a011D000000Oa2nQAC","parentDataSetId":"a011D000000Oa2fQAC","isEnforceStrictQueryFilter":false,"isParentSelected":false,"isChildSelected":true},{"id":"a0O1D0000007OSTUA2","name":"SBQQ__Product__c","childDataSetId":"a011D000000Oa2hQAC","parentDataSetId":"a011D000000Oa2fQAC","isEnforceStrictQueryFilter":false,"isParentSelected":false,"isChildSelected":true},{"id":"a0O1D0000007OStUAM","name":"SBQQ__TermDiscountSchedule__c","childDataSetId":"a011D000000Oa2fQAC","parentDataSetId":"a011D000000Oa2jQAC","isEnforceStrictQueryFilter":false,"isParentSelected":true,"isChildSelected":false},{"id":"a0O1D0000007OSuUAM","name":"SBQQ__DiscountSchedule__c","childDataSetId":"a011D000000Oa2fQAC","parentDataSetId":"a011D000000Oa2jQAC","isEnforceStrictQueryFilter":false,"isParentSelected":true,"isChildSelected":false},{"id":"a0O1D0000007OTGUA2","name":"SBQQ__DiscountCategory__c","childDataSetId":"a011D000000Oa2fQAC","parentDataSetId":"a011D000000Oa32QAC","isEnforceStrictQueryFilter":false,"isParentSelected":true,"isChildSelected":false},{"id":"a0O1D0000007OSlUAM","name":"SBQQ__SubscriptionTarget__c","childDataSetId":"a011D000000Oa2fQAC","parentDataSetId":"a011D000000Oa2fQAC","isEnforceStrictQueryFilter":false,"isParentSelected":true,"isChildSelected":false},{"id":"a0O1D0000007OSkUAM","name":"SBQQ__RenewalProduct__c","childDataSetId":"a011D000000Oa2fQAC","parentDataSetId":"a011D000000Oa2fQAC","isEnforceStrictQueryFilter":false,"isParentSelected":true,"isChildSelected":false},{"id":"a0O1D0000007OSjUAM","name":"SBQQ__UpgradeCredit__c","childDataSetId":"a011D000000Oa2fQAC","parentDataSetId":"a011D000000Oa2fQAC","isEnforceStrictQueryFilter":false,"isParentSelected":true,"isChildSelected":false},{"id":"a0O1D0000007OSiUAM","name":"SBQQ__UpgradeSource__c","childDataSetId":"a011D000000Oa2fQAC","parentDataSetId":"a011D000000Oa2fQAC","isEnforceStrictQueryFilter":false,"isParentSelected":true,"isChildSelected":false},{"id":"a0O1D0000007OShUAM","name":"SBQQ__UpgradeTarget__c","childDataSetId":"a011D000000Oa2fQAC","parentDataSetId":"a011D000000Oa2fQAC","isEnforceStrictQueryFilter":false,"isParentSelected":true,"isChildSelected":false}]},{"id":"a011D000000Oa31QAC","name":"Cost Element","sobjectName":"sbqq__cost__c","replicateOwner":false,"replicateRecordType":false,"createMissing":true,"syncPicklistValues":true,"setAuditFields":false,"ignoreNamespace":false,"ignoreRelationshipConstraints":false,"active":true,"root":false,"allFields":true,"overrideRootSettings":false,"useLocalSchema":false,"customUpsertRecordHandling":"Virtual External ID","dataSetFields":[],"relationships":[]},{"id":"a011D000000Oa2gQAC","name":"Additional Document Element","sobjectName":"sbqq__relatedcontent__c","replicateOwner":false,"replicateRecordType":false,"createMissing":true,"syncPicklistValues":true,"setAuditFields":false,"ignoreNamespace":false,"ignoreRelationshipConstraints":false,"active":true,"root":false,"allFields":true,"overrideRootSettings":false,"useLocalSchema":false,"customUpsertRecordHandling":"Virtual External ID","dataSetFields":[],"relationships":[]},{"id":"a011D000000Oa2nQAC","name":"Product Option Element","sobjectName":"sbqq__productoption__c","replicateOwner":false,"replicateRecordType":false,"createMissing":true,"syncPicklistValues":true,"setAuditFields":false,"ignoreNamespace":false,"ignoreRelationshipConstraints":false,"active":true,"root":false,"allFields":true,"overrideRootSettings":false,"useLocalSchema":false,"customUpsertRecordHandling":"Virtual External ID","dataSetFields":[],"relationships":[{"id":"a0O1D0000007OSvUAM","name":"SBQQ__DiscountSchedule__c","childDataSetId":"a011D000000Oa2nQAC","parentDataSetId":"a011D000000Oa2jQAC","isEnforceStrictQueryFilter":false,"isParentSelected":true,"isChildSelected":false}]},{"id":"a011D000000Oa2qQAC","name":"Option Constraint Element","sobjectName":"sbqq__optionconstraint__c","replicateOwner":false,"replicateRecordType":false,"createMissing":true,"syncPicklistValues":true,"setAuditFields":false,"ignoreNamespace":false,"ignoreRelationshipConstraints":false,"active":true,"root":false,"allFields":true,"overrideRootSettings":false,"useLocalSchema":false,"customUpsertRecordHandling":"Virtual External ID","dataSetFields":[],"relationships":[{"id":"a0O1D0000007OT2UAM","name":"SBQQ__ConstrainingOption__c","childDataSetId":"a011D000000Oa2qQAC","parentDataSetId":"a011D000000Oa2nQAC","isEnforceStrictQueryFilter":false,"isParentSelected":true,"isChildSelected":false},{"id":"a0O1D0000007OT1UAM","name":"SBQQ__ConstrainedOption__c","childDataSetId":"a011D000000Oa2qQAC","parentDataSetId":"a011D000000Oa2nQAC","isEnforceStrictQueryFilter":false,"isParentSelected":true,"isChildSelected":false}]},{"id":"a011D000000Oa2oQAC","name":"Product Attribute Element","sobjectName":"sbqq__productattribute__c","replicateOwner":false,"replicateRecordType":false,"createMissing":true,"syncPicklistValues":true,"setAuditFields":false,"ignoreNamespace":false,"ignoreRelationshipConstraints":false,"active":true,"root":false,"allFields":true,"overrideRootSettings":false,"useLocalSchema":false,"customUpsertRecordHandling":"Virtual External ID","dataSetFields":[],"relationships":[{"id":"a0O1D0000007OT0UAM","name":"SBQQ__Option__c","childDataSetId":"a011D000000Oa2oQAC","parentDataSetId":"a011D000000Oa2nQAC","isEnforceStrictQueryFilter":false,"isParentSelected":true,"isChildSelected":false}]},{"id":"a011D000000Oa2pQAC","name":"Configuration Attribute Element","sobjectName":"sbqq__configurationattribute__c","replicateOwner":false,"replicateRecordType":false,"createMissing":true,"syncPicklistValues":true,"setAuditFields":false,"ignoreNamespace":false,"ignoreRelationshipConstraints":false,"active":true,"root":false,"allFields":true,"overrideRootSettings":false,"useLocalSchema":false,"customUpsertRecordHandling":"Virtual External ID","dataSetFields":[],"relationships":[{"id":"a0O1D0000007OT3UAM","name":"SBQQ__Attribute__c","childDataSetId":"a011D000000Oa2oQAC","parentDataSetId":"a011D000000Oa2pQAC","isEnforceStrictQueryFilter":false,"isParentSelected":false,"isChildSelected":true}]},{"id":"a011D000000Oa2mQAC","name":"Product Feature Element","sobjectName":"sbqq__productfeature__c","replicateOwner":false,"replicateRecordType":false,"createMissing":true,"syncPicklistValues":true,"setAuditFields":false,"ignoreNamespace":false,"ignoreRelationshipConstraints":false,"active":true,"root":false,"allFields":true,"overrideRootSettings":false,"useLocalSchema":false,"customUpsertRecordHandling":"Virtual External ID","dataSetFields":[],"relationships":[{"id":"a0O1D0000007OSyUAM","name":"SBQQ__Feature__c","childDataSetId":"a011D000000Oa2pQAC","parentDataSetId":"a011D000000Oa2mQAC","isEnforceStrictQueryFilter":false,"isParentSelected":false,"isChildSelected":true},{"id":"a0O1D0000007OSxUAM","name":"SBQQ__Feature__c","childDataSetId":"a011D000000Oa2oQAC","parentDataSetId":"a011D000000Oa2mQAC","isEnforceStrictQueryFilter":false,"isParentSelected":false,"isChildSelected":true},{"id":"a0O1D0000007OSwUAM","name":"SBQQ__Feature__c","childDataSetId":"a011D000000Oa2nQAC","parentDataSetId":"a011D000000Oa2mQAC","isEnforceStrictQueryFilter":false,"isParentSelected":false,"isChildSelected":true},{"id":"a0O1D0000007OSsUAM","name":"SBQQ__DiscountSchedule__c","childDataSetId":"a011D000000Oa2mQAC","parentDataSetId":"a011D000000Oa2jQAC","isEnforceStrictQueryFilter":false,"isParentSelected":true,"isChildSelected":false}]},{"id":"a011D000000Oa2rQAC","name":"Configuration Rule Element","sobjectName":"sbqq__configurationrule__c","replicateOwner":false,"replicateRecordType":false,"createMissing":true,"syncPicklistValues":true,"setAuditFields":false,"ignoreNamespace":false,"ignoreRelationshipConstraints":false,"active":true,"root":false,"allFields":true,"overrideRootSettings":false,"useLocalSchema":false,"customUpsertRecordHandling":"Virtual External ID","dataSetFields":[],"relationships":[{"id":"a0O1D0000007OT6UAM","name":"SBQQ__ProductRule__c","childDataSetId":"a011D000000Oa2rQAC","parentDataSetId":"a011D000000Oa2sQAC","isEnforceStrictQueryFilter":false,"isParentSelected":true,"isChildSelected":false},{"id":"a0O1D0000007OSzUAM","name":"SBQQ__ProductFeature__c","childDataSetId":"a011D000000Oa2rQAC","parentDataSetId":"a011D000000Oa2mQAC","isEnforceStrictQueryFilter":false,"isParentSelected":true,"isChildSelected":false}]},{"id":"a011D000000Oa2sQAC","name":"Product Rule Element","sobjectName":"sbqq__productrule__c","replicateOwner":false,"replicateRecordType":false,"createMissing":true,"syncPicklistValues":true,"setAuditFields":false,"ignoreNamespace":false,"ignoreRelationshipConstraints":false,"active":true,"root":false,"allFields":true,"overrideRootSettings":false,"useLocalSchema":false,"customUpsertRecordHandling":"Virtual External ID","dataSetFields":[{"id":"a021D000000yjoYQAQ","name":"SBQQ__ConditionsMet__c","externalId":false,"createMissing":false,"syncPicklistValues":false,"setEmpty":false,"scrambleValue":false,"fixedValue":false,"delayInsert":false,"deployLast":true,"temporaryInsertValue":"All","copyRelationshipValue":false}],"relationships":[{"id":"a0O1D0000007OT4UAM","name":"SBQQ__Rule__c","childDataSetId":"a011D000000Oa2tQAC","parentDataSetId":"a011D000000Oa2sQAC","isEnforceStrictQueryFilter":false,"isParentSelected":false,"isChildSelected":true}]},{"id":"a011D000000Oa2zQAC","name":"Product Action Element","sobjectName":"sbqq__productaction__c","replicateOwner":false,"replicateRecordType":false,"createMissing":true,"syncPicklistValues":true,"setAuditFields":false,"ignoreNamespace":false,"ignoreRelationshipConstraints":false,"active":true,"root":false,"allFields":true,"overrideRootSettings":false,"useLocalSchema":false,"customUpsertRecordHandling":"Virtual External ID","dataSetFields":[],"relationships":[{"id":"a0O1D0000007OT5UAM","name":"SBQQ__Rule__c","childDataSetId":"a011D000000Oa2zQAC","parentDataSetId":"a011D000000Oa2sQAC","isEnforceStrictQueryFilter":false,"isParentSelected":true,"isChildSelected":false}]},{"id":"a011D000000Oa2tQAC","name":"Error Condition Element","sobjectName":"sbqq__errorcondition__c","replicateOwner":false,"replicateRecordType":false,"createMissing":true,"syncPicklistValues":true,"setAuditFields":false,"ignoreNamespace":false,"ignoreRelationshipConstraints":false,"active":true,"root":false,"allFields":true,"overrideRootSettings":false,"useLocalSchema":false,"customUpsertRecordHandling":"Virtual External ID","dataSetFields":[],"relationships":[{"id":"a0O1D0000007OT7UAM","name":"SBQQ__FilterVariable__c","childDataSetId":"a011D000000Oa2tQAC","parentDataSetId":"a011D000000Oa2uQAC","isEnforceStrictQueryFilter":false,"isParentSelected":true,"isChildSelected":false},{"id":"a0O1D0000007OTHUA2","name":"SBQQ__TestedVariable__c","childDataSetId":"a011D000000Oa2tQAC","parentDataSetId":"a011D000000Oa2uQAC","isEnforceStrictQueryFilter":false,"isParentSelected":true,"isChildSelected":false}]},{"id":"a011D000000Oa2uQAC","name":"Summary Variable Element","sobjectName":"sbqq__summaryvariable__c","replicateOwner":false,"replicateRecordType":false,"createMissing":true,"syncPicklistValues":true,"setAuditFields":false,"ignoreNamespace":false,"ignoreRelationshipConstraints":false,"active":true,"root":false,"allFields":true,"overrideRootSettings":false,"useLocalSchema":false,"dataSetFields":[],"relationships":[{"id":"a0O1D0000007OT8UAM","name":"SBQQ__CombineWith__c","childDataSetId":"a011D000000Oa2uQAC","parentDataSetId":"a011D000000Oa2uQAC","isEnforceStrictQueryFilter":false,"isParentSelected":true,"isChildSelected":false}]},{"id":"a011D000000Oa2vQAC","name":"Price Condition Element","sobjectName":"sbqq__pricecondition__c","replicateOwner":false,"replicateRecordType":false,"createMissing":true,"syncPicklistValues":true,"setAuditFields":false,"ignoreNamespace":false,"ignoreRelationshipConstraints":false,"active":true,"root":false,"allFields":true,"overrideRootSettings":false,"useLocalSchema":false,"customUpsertRecordHandling":"Virtual External ID","dataSetFields":[],"relationships":[{"id":"a0O1D0000007OT9UAM","name":"SBQQ__FilterVariable__c","childDataSetId":"a011D000000Oa2vQAC","parentDataSetId":"a011D000000Oa2uQAC","isEnforceStrictQueryFilter":false,"isParentSelected":true,"isChildSelected":false},{"id":"a0O1D0000007OTAUA2","name":"SBQQ__TestedVariable__c","childDataSetId":"a011D000000Oa2vQAC","parentDataSetId":"a011D000000Oa2uQAC","isEnforceStrictQueryFilter":false,"isParentSelected":true,"isChildSelected":false}]},{"id":"a011D000000Oa2wQAC","name":"Price Rule Element","sobjectName":"sbqq__pricerule__c","replicateOwner":false,"replicateRecordType":false,"createMissing":true,"syncPicklistValues":true,"setAuditFields":false,"ignoreNamespace":false,"ignoreRelationshipConstraints":false,"active":true,"root":false,"allFields":true,"overrideRootSettings":false,"useLocalSchema":false,"customUpsertRecordHandling":"Virtual External ID","dataSetFields":[{"id":"a021D000000yjoZQAQ","name":"SBQQ__ConditionsMet__c","externalId":false,"createMissing":false,"syncPicklistValues":false,"setEmpty":false,"scrambleValue":false,"fixedValue":false,"delayInsert":false,"deployLast":true,"temporaryInsertValue":"All","copyRelationshipValue":false}],"relationships":[{"id":"a0O1D0000007OTDUA2","name":"SBQQ__Rule__c","childDataSetId":"a011D000000Oa2vQAC","parentDataSetId":"a011D000000Oa2wQAC","isEnforceStrictQueryFilter":false,"isParentSelected":false,"isChildSelected":true},{"id":"a0O1D0000007OTFUA2","name":"SBQQ__PriceRule2__c","childDataSetId":"a011D000000Oa2yQAC","parentDataSetId":"a011D000000Oa2wQAC","isEnforceStrictQueryFilter":false,"isParentSelected":false,"isChildSelected":true},{"id":"a0O1D0000007OTEUA2","name":"SBQQ__Rule__c","childDataSetId":"a011D000000Oa2xQAC","parentDataSetId":"a011D000000Oa2wQAC","isEnforceStrictQueryFilter":false,"isParentSelected":false,"isChildSelected":true}]},{"id":"a011D000000Oa2yQAC","name":"Lookup Query Element","sobjectName":"sbqq__lookupquery__c","replicateOwner":false,"replicateRecordType":false,"createMissing":true,"syncPicklistValues":true,"setAuditFields":false,"ignoreNamespace":false,"ignoreRelationshipConstraints":false,"active":true,"root":false,"allFields":true,"overrideRootSettings":false,"useLocalSchema":false,"customUpsertRecordHandling":"Virtual External ID","dataSetFields":[],"relationships":[]},{"id":"a011D000000Oa2xQAC","name":"Price Action Element","sobjectName":"sbqq__priceaction__c","replicateOwner":false,"replicateRecordType":false,"createMissing":true,"syncPicklistValues":true,"setAuditFields":false,"ignoreNamespace":false,"ignoreRelationshipConstraints":false,"active":true,"root":false,"allFields":true,"overrideRootSettings":false,"useLocalSchema":false,"customUpsertRecordHandling":"Virtual External ID","dataSetFields":[],"relationships":[{"id":"a0O1D0000007OTBUA2","name":"SBQQ__SourceVariable__c","childDataSetId":"a011D000000Oa2xQAC","parentDataSetId":"a011D000000Oa2uQAC","isEnforceStrictQueryFilter":false,"isParentSelected":true,"isChildSelected":false}]},{"id":"a011D000000Oa2jQAC","name":"Discount Schedule Element","sobjectName":"sbqq__discountschedule__c","replicateOwner":false,"replicateRecordType":false,"createMissing":true,"syncPicklistValues":true,"setAuditFields":false,"ignoreNamespace":false,"ignoreRelationshipConstraints":false,"active":true,"root":false,"allFields":true,"overrideRootSettings":false,"useLocalSchema":false,"customUpsertRecordHandling":"Virtual External ID","dataSetFields":[],"relationships":[{"id":"a0O1D0000007OSpUAM","name":"SBQQ__Schedule__c","childDataSetId":"a011D000000Oa2kQAC","parentDataSetId":"a011D000000Oa2jQAC","isEnforceStrictQueryFilter":false,"isParentSelected":false,"isChildSelected":true},{"id":"a0O1D0000007OSqUAM","name":"SBQQ__DiscountSchedule__c","childDataSetId":"a011D000000Oa2lQAC","parentDataSetId":"a011D000000Oa2jQAC","isEnforceStrictQueryFilter":false,"isParentSelected":false,"isChildSelected":true},{"id":"a0O1D0000007OSrUAM","name":"SBQQ__TermDiscountSchedule__c","childDataSetId":"a011D000000Oa2lQAC","parentDataSetId":"a011D000000Oa2jQAC","isEnforceStrictQueryFilter":false,"isParentSelected":false,"isChildSelected":true},{"id":"a0O1D0000007OSoUAM","name":"SBQQ__Pricebook__c","childDataSetId":"a011D000000Oa2jQAC","parentDataSetId":"a011D000000Oa2iQAC","isEnforceStrictQueryFilter":false,"isParentSelected":true,"isChildSelected":false}]},{"id":"a011D000000Oa2kQAC","name":"Discount Tier Element","sobjectName":"sbqq__discounttier__c","replicateOwner":false,"replicateRecordType":false,"createMissing":true,"syncPicklistValues":true,"setAuditFields":false,"ignoreNamespace":false,"ignoreRelationshipConstraints":false,"active":true,"root":false,"allFields":true,"overrideRootSettings":false,"useLocalSchema":false,"customUpsertRecordHandling":"Virtual External ID","dataSetFields":[],"relationships":[]},{"id":"a011D000000Oa2lQAC","name":"Price Dimension Element","sobjectName":"sbqq__dimension__c","replicateOwner":false,"replicateRecordType":false,"createMissing":true,"syncPicklistValues":true,"setAuditFields":false,"ignoreNamespace":false,"ignoreRelationshipConstraints":false,"active":true,"root":false,"allFields":true,"overrideRootSettings":false,"useLocalSchema":false,"customUpsertRecordHandling":"Virtual External ID","dataSetFields":[],"relationships":[]},{"id":"a011D000000Oa2iQAC","name":"Price Book Element","sobjectName":"pricebook2","replicateOwner":false,"replicateRecordType":false,"createMissing":true,"syncPicklistValues":true,"setAuditFields":false,"ignoreNamespace":false,"ignoreRelationshipConstraints":false,"active":true,"root":false,"allFields":true,"overrideRootSettings":false,"useLocalSchema":false,"customUpsertRecordHandling":"Virtual External ID","dataSetFields":[],"relationships":[]},{"id":"a011D000000Oa2hQAC","name":"Block Price Element","sobjectName":"sbqq__blockprice__c","replicateOwner":false,"replicateRecordType":false,"createMissing":true,"syncPicklistValues":true,"setAuditFields":false,"ignoreNamespace":false,"ignoreRelationshipConstraints":false,"active":true,"root":false,"allFields":true,"overrideRootSettings":false,"useLocalSchema":false,"customUpsertRecordHandling":"Virtual External ID","dataSetFields":[],"relationships":[{"id":"a0O1D0000007OSnUAM","name":"SBQQ__PriceBook2__c","childDataSetId":"a011D000000Oa2hQAC","parentDataSetId":"a011D000000Oa2iQAC","isEnforceStrictQueryFilter":false,"isParentSelected":true,"isChildSelected":false}]},{"id":"a011D000000Oa30QAC","name":"Upgrade Source Element","sobjectName":"sbqq__upgradesource__c","replicateOwner":false,"replicateRecordType":false,"createMissing":true,"syncPicklistValues":true,"setAuditFields":false,"ignoreNamespace":false,"ignoreRelationshipConstraints":false,"active":true,"root":false,"allFields":true,"overrideRootSettings":false,"useLocalSchema":false,"customUpsertRecordHandling":"Virtual External ID","dataSetFields":[],"relationships":[]},{"id":"a011D000000Oa32QAC","name":"Discount Category Element","sobjectName":"sbqq__discountcategory__c","replicateOwner":false,"replicateRecordType":false,"createMissing":true,"syncPicklistValues":true,"setAuditFields":false,"ignoreNamespace":false,"ignoreRelationshipConstraints":false,"active":true,"root":false,"allFields":true,"overrideRootSettings":false,"useLocalSchema":false,"customUpsertRecordHandling":"Virtual External ID","dataSetFields":[],"relationships":[]}]}