{"header":{"version":"1.0"},"dataSets":[{"id":"a171I0000017WstQAE","name":"SBQQ 212 CEID Localization Data Set","sobjectName":"sbqq__localization__c","replicateOwner":false,"replicateRecordType":false,"createMissing":true,"syncPicklistValues":true,"setAuditFields":false,"ignoreNamespace":false,"ignoreRelationshipConstraints":false,"active":true,"root":true,"allFields":true,"overrideRootSettings":false,"useLocalSchema":true,"customUpsertRecordHandling":"Standard Upsert","recordSelectionLimit":0,"bulkBatchSize":0,"originConnection":{"name":"SFDC CPQ Spring '18"},"dataSetFields":[{"id":"a181I0000012BESQA2","name":"SBQQ__APIName__c","externalId":true,"createMissing":false,"syncPicklistValues":false,"setEmpty":false,"scrambleValue":false,"fixedValue":false,"delayInsert":false,"deployLast":false,"copyRelationshipValue":false},{"id":"a181I0000012BETQA2","name":"SBQQ__Language__c","externalId":true,"createMissing":false,"syncPicklistValues":false,"setEmpty":false,"scrambleValue":false,"fixedValue":false,"delayInsert":false,"deployLast":false,"copyRelationshipValue":false},{"id":"a181I0000012BEUQA2","name":"SBQQ__LineColumn__c","externalId":true,"createMissing":false,"syncPicklistValues":false,"setEmpty":false,"scrambleValue":false,"fixedValue":false,"delayInsert":false,"deployLast":false,"copyRelationshipValue":false},{"id":"a181I0000012BEVQA2","name":"SBQQ__PriceDimension__c","externalId":true,"createMissing":false,"syncPicklistValues":false,"setEmpty":false,"scrambleValue":false,"fixedValue":false,"delayInsert":false,"deployLast":false,"copyRelationshipValue":false},{"id":"a181I0000012BEWQA2","name":"SBQQ__ProductFeature__c","externalId":true,"createMissing":false,"syncPicklistValues":false,"setEmpty":false,"scrambleValue":false,"fixedValue":false,"delayInsert":false,"deployLast":false,"copyRelationshipValue":false},{"id":"a181I0000012BEXQA2","name":"SBQQ__ProductOption__c","externalId":true,"createMissing":false,"syncPicklistValues":false,"setEmpty":false,"scrambleValue":false,"fixedValue":false,"delayInsert":false,"deployLast":false,"copyRelationshipValue":false},{"id":"a181I0000012BEYQA2","name":"SBQQ__Product__c","externalId":true,"createMissing":false,"syncPicklistValues":false,"setEmpty":false,"scrambleValue":false,"fixedValue":false,"delayInsert":false,"deployLast":false,"copyRelationshipValue":false},{"id":"a181I0000012BEZQA2","name":"SBQQ__QuoteTemplate__c","externalId":true,"createMissing":false,"syncPicklistValues":false,"setEmpty":false,"scrambleValue":false,"fixedValue":false,"delayInsert":false,"deployLast":false,"copyRelationshipValue":false},{"id":"a181I0000012BEaQAM","name":"SBQQ__QuoteTerm__c","externalId":true,"createMissing":false,"syncPicklistValues":false,"setEmpty":false,"scrambleValue":false,"fixedValue":false,"delayInsert":false,"deployLast":false,"copyRelationshipValue":false},{"id":"a181I0000012BEbQAM","name":"SBQQ__TemplateContent__c","externalId":true,"createMissing":false,"syncPicklistValues":false,"setEmpty":false,"scrambleValue":false,"fixedValue":false,"delayInsert":false,"deployLast":false,"copyRelationshipValue":false}],"relationships":[{"id":"a1G1I000000WJOHUA4","name":"SBQQ__Localization__c","childDataSetId":"a171I0000017WsuQAE","parentDataSetId":"a171I0000017WstQAE","isEnforceStrictQueryFilter":false,"isParentSelected":true,"isChildSelected":true},{"id":"a1G1I000000WJOLUA4","name":"SBQQ__TemplateContent__c","childDataSetId":"a171I0000017WstQAE","parentDataSetId":"a171I0000017WsyQAE","isEnforceStrictQueryFilter":false,"isParentSelected":true,"isChildSelected":false},{"id":"a1G1I000000WJOKUA4","name":"SBQQ__QuoteTemplate__c","childDataSetId":"a171I0000017WstQAE","parentDataSetId":"a171I0000017WsxQAE","isEnforceStrictQueryFilter":false,"isParentSelected":true,"isChildSelected":false},{"id":"a1G1I000000WJOJUA4","name":"SBQQ__Product__c","childDataSetId":"a171I0000017WstQAE","parentDataSetId":"a171I0000017WswQAE","isEnforceStrictQueryFilter":false,"isParentSelected":true,"isChildSelected":false},{"id":"a1G1I000000WJOIUA4","name":"SBQQ__ProductOption__c","childDataSetId":"a171I0000017WstQAE","parentDataSetId":"a171I0000017WsvQAE","isEnforceStrictQueryFilter":false,"isParentSelected":true,"isChildSelected":false},{"id":"a1G1I000000WJOMUA4","name":"SBQQ__ProductFeature__c","childDataSetId":"a171I0000017WstQAE","parentDataSetId":"a171I0000017WszQAE","isEnforceStrictQueryFilter":false,"isParentSelected":true,"isChildSelected":false},{"id":"a1G1I000000WJOPUA4","name":"SBQQ__LineColumn__c","childDataSetId":"a171I0000017WstQAE","parentDataSetId":"a171I0000017Wt2QAE","isEnforceStrictQueryFilter":false,"isParentSelected":true,"isChildSelected":false},{"id":"a1G1I000000WJOOUA4","name":"SBQQ__PriceDimension__c","childDataSetId":"a171I0000017WstQAE","parentDataSetId":"a171I0000017Wt1QAE","isEnforceStrictQueryFilter":false,"isParentSelected":true,"isChildSelected":false},{"id":"a1G1I000000WJONUA4","name":"SBQQ__QuoteTerm__c","childDataSetId":"a171I0000017WstQAE","parentDataSetId":"a171I0000017Wt0QAE","isEnforceStrictQueryFilter":false,"isParentSelected":true,"isChildSelected":false}]},{"id":"a171I0000017WsuQAE","name":"Search Index","sobjectName":"sbqq__searchindex__c","replicateOwner":false,"replicateRecordType":false,"createMissing":true,"syncPicklistValues":true,"setAuditFields":false,"ignoreNamespace":false,"ignoreRelationshipConstraints":false,"active":true,"root":false,"allFields":true,"overrideRootSettings":false,"useLocalSchema":false,"recordSelectionLimit":0,"bulkBatchSize":0,"dataSetFields":[],"relationships":[]},{"id":"a171I0000017WsyQAE","name":"Template Content","sobjectName":"sbqq__templatecontent__c","replicateOwner":false,"replicateRecordType":false,"createMissing":true,"syncPicklistValues":true,"setAuditFields":false,"ignoreNamespace":false,"ignoreRelationshipConstraints":false,"active":true,"root":false,"allFields":true,"overrideRootSettings":false,"useLocalSchema":false,"customUpsertRecordHandling":"Standard Upsert","recordSelectionLimit":0,"bulkBatchSize":0,"dataSetFields":[{"id":"a181I0000012BEkQAM","name":"Name","externalId":true,"createMissing":false,"syncPicklistValues":false,"setEmpty":false,"scrambleValue":false,"fixedValue":false,"delayInsert":false,"deployLast":false,"copyRelationshipValue":false}],"relationships":[]},{"id":"a171I0000017WsxQAE","name":"Quote Template","sobjectName":"sbqq__quotetemplate__c","replicateOwner":false,"replicateRecordType":false,"createMissing":true,"syncPicklistValues":true,"setAuditFields":false,"ignoreNamespace":false,"ignoreRelationshipConstraints":false,"active":true,"root":false,"allFields":true,"overrideRootSettings":false,"useLocalSchema":false,"customUpsertRecordHandling":"Standard Upsert","recordSelectionLimit":0,"bulkBatchSize":0,"dataSetFields":[{"id":"a181I0000012BEjQAM","name":"Name","externalId":true,"createMissing":false,"syncPicklistValues":false,"setEmpty":false,"scrambleValue":false,"fixedValue":false,"delayInsert":false,"deployLast":false,"copyRelationshipValue":false}],"relationships":[]},{"id":"a171I0000017WswQAE","name":"Product Data Set","sobjectName":"product2","replicateOwner":false,"replicateRecordType":false,"createMissing":true,"syncPicklistValues":true,"setAuditFields":false,"ignoreNamespace":false,"ignoreRelationshipConstraints":false,"active":true,"root":false,"allFields":true,"overrideRootSettings":false,"useLocalSchema":false,"customUpsertRecordHandling":"Standard Upsert","recordSelectionLimit":0,"bulkBatchSize":0,"dataSetFields":[{"id":"a181I0000012BEgQAM","name":"Name","externalId":true,"createMissing":false,"syncPicklistValues":false,"setEmpty":false,"scrambleValue":false,"fixedValue":false,"delayInsert":false,"deployLast":false,"copyRelationshipValue":false},{"id":"a181I0000012BEhQAM","name":"ProductCode","externalId":true,"createMissing":false,"syncPicklistValues":false,"setEmpty":false,"scrambleValue":false,"fixedValue":false,"delayInsert":false,"deployLast":false,"copyRelationshipValue":false},{"id":"a181I0000012BEiQAM","name":"IsActive","externalId":true,"createMissing":false,"syncPicklistValues":false,"setEmpty":false,"scrambleValue":false,"fixedValue":false,"delayInsert":false,"deployLast":false,"copyRelationshipValue":false}],"relationships":[]},{"id":"a171I0000017WsvQAE","name":"Product Option","sobjectName":"sbqq__productoption__c","replicateOwner":false,"replicateRecordType":false,"createMissing":true,"syncPicklistValues":true,"setAuditFields":false,"ignoreNamespace":false,"ignoreRelationshipConstraints":false,"active":true,"root":false,"allFields":true,"overrideRootSettings":false,"useLocalSchema":false,"customUpsertRecordHandling":"Standard Upsert","recordSelectionLimit":0,"bulkBatchSize":0,"dataSetFields":[{"id":"a181I0000012BEcQAM","name":"SBQQ__Feature__c","externalId":true,"createMissing":false,"syncPicklistValues":false,"setEmpty":false,"scrambleValue":false,"fixedValue":false,"delayInsert":false,"deployLast":false,"copyRelationshipValue":false},{"id":"a181I0000012BEdQAM","name":"SBQQ__ConfiguredSKU__c","externalId":true,"createMissing":false,"syncPicklistValues":false,"setEmpty":false,"scrambleValue":false,"fixedValue":false,"delayInsert":false,"deployLast":false,"copyRelationshipValue":false},{"id":"a181I0000012BEeQAM","name":"SBQQ__Number__c","externalId":true,"createMissing":false,"syncPicklistValues":false,"setEmpty":false,"scrambleValue":false,"fixedValue":false,"delayInsert":false,"deployLast":false,"copyRelationshipValue":false},{"id":"a181I0000012BEfQAM","name":"SBQQ__OptionalSKU__c","externalId":true,"createMissing":false,"syncPicklistValues":false,"setEmpty":false,"scrambleValue":false,"fixedValue":false,"delayInsert":false,"deployLast":false,"copyRelationshipValue":false}],"relationships":[]},{"id":"a171I0000017WszQAE","name":"Product Feature","sobjectName":"sbqq__productfeature__c","replicateOwner":false,"replicateRecordType":false,"createMissing":true,"syncPicklistValues":true,"setAuditFields":false,"ignoreNamespace":false,"ignoreRelationshipConstraints":false,"active":true,"root":false,"allFields":true,"overrideRootSettings":false,"useLocalSchema":false,"customUpsertRecordHandling":"Standard Upsert","recordSelectionLimit":0,"bulkBatchSize":0,"dataSetFields":[{"id":"a181I0000012BElQAM","name":"Name","externalId":true,"createMissing":false,"syncPicklistValues":false,"setEmpty":false,"scrambleValue":false,"fixedValue":false,"delayInsert":false,"deployLast":false,"copyRelationshipValue":false},{"id":"a181I0000012BEmQAM","name":"SBQQ__ConfiguredSKU__c","externalId":true,"createMissing":false,"syncPicklistValues":false,"setEmpty":false,"scrambleValue":false,"fixedValue":false,"delayInsert":false,"deployLast":false,"copyRelationshipValue":false}],"relationships":[]},{"id":"a171I0000017Wt2QAE","name":"Line Column","sobjectName":"sbqq__linecolumn__c","replicateOwner":false,"replicateRecordType":false,"createMissing":true,"syncPicklistValues":true,"setAuditFields":false,"ignoreNamespace":false,"ignoreRelationshipConstraints":false,"active":true,"root":false,"allFields":true,"overrideRootSettings":false,"useLocalSchema":false,"customUpsertRecordHandling":"Standard Upsert","recordSelectionLimit":0,"bulkBatchSize":0,"dataSetFields":[{"id":"a181I0000012BEyQAM","name":"Name","externalId":true,"createMissing":false,"syncPicklistValues":false,"setEmpty":false,"scrambleValue":false,"fixedValue":false,"delayInsert":false,"deployLast":false,"copyRelationshipValue":false},{"id":"a181I0000012BEzQAM","name":"SBQQ__Section__c","externalId":true,"createMissing":false,"syncPicklistValues":false,"setEmpty":false,"scrambleValue":false,"fixedValue":false,"delayInsert":false,"deployLast":false,"copyRelationshipValue":false},{"id":"a181I0000012BF0QAM","name":"SBQQ__Template__c","externalId":true,"createMissing":false,"syncPicklistValues":false,"setEmpty":false,"scrambleValue":false,"fixedValue":false,"delayInsert":false,"deployLast":false,"copyRelationshipValue":false}],"relationships":[]},{"id":"a171I0000017Wt1QAE","name":"Price Dimension","sobjectName":"sbqq__dimension__c","replicateOwner":false,"replicateRecordType":false,"createMissing":true,"syncPicklistValues":true,"setAuditFields":false,"ignoreNamespace":false,"ignoreRelationshipConstraints":false,"active":true,"root":false,"allFields":true,"overrideRootSettings":false,"useLocalSchema":false,"customUpsertRecordHandling":"Standard Upsert","recordSelectionLimit":0,"bulkBatchSize":0,"dataSetFields":[{"id":"a181I0000012BEsQAM","name":"Name","externalId":true,"createMissing":false,"syncPicklistValues":false,"setEmpty":false,"scrambleValue":false,"fixedValue":false,"delayInsert":false,"deployLast":false,"copyRelationshipValue":false},{"id":"a181I0000012BEtQAM","name":"SBQQ__Product__c","externalId":true,"createMissing":false,"syncPicklistValues":false,"setEmpty":false,"scrambleValue":false,"fixedValue":false,"delayInsert":false,"deployLast":false,"copyRelationshipValue":false},{"id":"a181I0000012BEuQAM","name":"SBQQ__Type__c","externalId":true,"createMissing":false,"syncPicklistValues":false,"setEmpty":false,"scrambleValue":false,"fixedValue":false,"delayInsert":false,"deployLast":false,"copyRelationshipValue":false},{"id":"a181I0000012BEvQAM","name":"SBQQ__DiscountSchedule__c","externalId":true,"createMissing":false,"syncPicklistValues":false,"setEmpty":false,"scrambleValue":false,"fixedValue":false,"delayInsert":false,"deployLast":false,"copyRelationshipValue":false},{"id":"a181I0000012BEwQAM","name":"SBQQ__TermDiscountSchedule__c","externalId":true,"createMissing":false,"syncPicklistValues":false,"setEmpty":false,"scrambleValue":false,"fixedValue":false,"delayInsert":false,"deployLast":false,"copyRelationshipValue":false},{"id":"a181I0000012BExQAM","name":"CurrencyIsoCode","externalId":true,"createMissing":false,"syncPicklistValues":false,"setEmpty":false,"scrambleValue":false,"fixedValue":false,"delayInsert":false,"deployLast":false,"copyRelationshipValue":false}],"relationships":[]},{"id":"a171I0000017Wt0QAE","name":"Quote Term","sobjectName":"sbqq__quoteterm__c","replicateOwner":false,"replicateRecordType":false,"createMissing":true,"syncPicklistValues":true,"setAuditFields":false,"ignoreNamespace":false,"ignoreRelationshipConstraints":false,"active":true,"root":false,"allFields":true,"overrideRootSettings":false,"useLocalSchema":false,"customUpsertRecordHandling":"Standard Upsert","recordSelectionLimit":0,"bulkBatchSize":0,"dataSetFields":[{"id":"a181I0000012BEnQAM","name":"SBQQ__PrintOrder__c","externalId":true,"createMissing":false,"syncPicklistValues":false,"setEmpty":false,"scrambleValue":false,"fixedValue":false,"delayInsert":false,"deployLast":false,"copyRelationshipValue":false},{"id":"a181I0000012BEoQAM","name":"SBQQ__Status__c","externalId":true,"createMissing":false,"syncPicklistValues":false,"setEmpty":false,"scrambleValue":false,"fixedValue":false,"delayInsert":false,"deployLast":false,"copyRelationshipValue":false},{"id":"a181I0000012BEpQAM","name":"SBQQ__Type__c","externalId":true,"createMissing":false,"syncPicklistValues":false,"setEmpty":false,"scrambleValue":false,"fixedValue":false,"delayInsert":false,"deployLast":false,"copyRelationshipValue":false},{"id":"a181I0000012BEqQAM","name":"SBQQ__ConditionsMet__c","externalId":true,"createMissing":false,"syncPicklistValues":false,"setEmpty":false,"scrambleValue":false,"fixedValue":false,"delayInsert":false,"deployLast":false,"copyRelationshipValue":false},{"id":"a181I0000012BErQAM","name":"SBQQ__Active__c","externalId":true,"createMissing":false,"syncPicklistValues":false,"setEmpty":false,"scrambleValue":false,"fixedValue":false,"delayInsert":false,"deployLast":false,"copyRelationshipValue":false}],"relationships":[]}]}