{"header":{"version":"1.0"},"dataSets":[{"id":"a171I0000017KtLQAU","name":"SBQQ 210 CEID Price Rule Data Set","sobjectName":"sbqq__pricerule__c","replicateOwner":false,"replicateRecordType":false,"createMissing":true,"syncPicklistValues":true,"setAuditFields":false,"ignoreNamespace":false,"ignoreRelationshipConstraints":false,"active":true,"root":true,"allFields":true,"overrideRootSettings":false,"useLocalSchema":true,"customUpsertRecordHandling":"Standard Upsert","recordSelectionLimit":0,"bulkBatchSize":0,"originConnection":{"name":"PROD - Salesforce Hitech ver 210.15.7"},"dataSetFields":[{"id":"a181I00000123PeQAI","name":"Name","externalId":true,"createMissing":false,"syncPicklistValues":false,"setEmpty":false,"scrambleValue":false,"fixedValue":false,"delayInsert":false,"deployLast":false,"copyRelationshipValue":false},{"id":"a181I00000123PfQAI","name":"SBQQ__Active__c","externalId":true,"createMissing":false,"syncPicklistValues":false,"setEmpty":false,"scrambleValue":false,"fixedValue":false,"delayInsert":false,"deployLast":false,"copyRelationshipValue":false},{"id":"a181I00000123PgQAI","name":"SBQQ__Product__c","externalId":true,"createMissing":false,"syncPicklistValues":false,"setEmpty":false,"scrambleValue":false,"fixedValue":false,"delayInsert":false,"deployLast":false,"copyRelationshipValue":false}],"relationships":[{"id":"a1G1I000000WFB8UAO","name":"SBQQ__PriceRule2__c","childDataSetId":"a171I0000017KtPQAU","parentDataSetId":"a171I0000017KtLQAU","isEnforceStrictQueryFilter":false,"isParentSelected":true,"isChildSelected":true},{"id":"a1G1I000000WFB6UAO","name":"SBQQ__Rule__c","childDataSetId":"a171I0000017KtMQAU","parentDataSetId":"a171I0000017KtLQAU","isEnforceStrictQueryFilter":false,"isParentSelected":true,"isChildSelected":true},{"id":"a1G1I000000WFB7UAO","name":"SBQQ__Rule__c","childDataSetId":"a171I0000017KtOQAU","parentDataSetId":"a171I0000017KtLQAU","isEnforceStrictQueryFilter":false,"isParentSelected":true,"isChildSelected":true}]},{"id":"a171I0000017KtPQAU","name":"Lookup Query Element","sobjectName":"sbqq__lookupquery__c","replicateOwner":false,"replicateRecordType":false,"createMissing":true,"syncPicklistValues":true,"setAuditFields":false,"ignoreNamespace":false,"ignoreRelationshipConstraints":false,"active":true,"root":false,"allFields":true,"overrideRootSettings":false,"useLocalSchema":false,"customUpsertRecordHandling":"Standard Upsert","recordSelectionLimit":0,"bulkBatchSize":0,"dataSetFields":[{"id":"a181I00000123PyQAI","name":"SBQQ__LookupField__c","externalId":true,"createMissing":false,"syncPicklistValues":false,"setEmpty":false,"scrambleValue":false,"fixedValue":false,"delayInsert":false,"deployLast":false,"copyRelationshipValue":false},{"id":"a181I00000123PzQAI","name":"SBQQ__MatchType__c","externalId":true,"createMissing":false,"syncPicklistValues":false,"setEmpty":false,"scrambleValue":false,"fixedValue":false,"delayInsert":false,"deployLast":false,"copyRelationshipValue":false},{"id":"a181I00000123Q0QAI","name":"SBQQ__Operator__c","externalId":true,"createMissing":false,"syncPicklistValues":false,"setEmpty":false,"scrambleValue":false,"fixedValue":false,"delayInsert":false,"deployLast":false,"copyRelationshipValue":false},{"id":"a181I00000123Q1QAI","name":"SBQQ__TestedField__c","externalId":true,"createMissing":false,"syncPicklistValues":false,"setEmpty":false,"scrambleValue":false,"fixedValue":false,"delayInsert":false,"deployLast":false,"copyRelationshipValue":false},{"id":"a181I00000123Q2QAI","name":"SBQQ__TestedObject__c","externalId":true,"createMissing":false,"syncPicklistValues":false,"setEmpty":false,"scrambleValue":false,"fixedValue":false,"delayInsert":false,"deployLast":false,"copyRelationshipValue":false},{"id":"a181I00000123Q3QAI","name":"SBQQ__TestedValue__c","externalId":true,"createMissing":false,"syncPicklistValues":false,"setEmpty":false,"scrambleValue":false,"fixedValue":false,"delayInsert":false,"deployLast":false,"copyRelationshipValue":false},{"id":"a181I00000123Q4QAI","name":"SBQQ__PriceRule2__c","externalId":true,"createMissing":false,"syncPicklistValues":false,"setEmpty":false,"scrambleValue":false,"fixedValue":false,"delayInsert":false,"deployLast":false,"copyRelationshipValue":false}],"relationships":[]},{"id":"a171I0000017KtMQAU","name":"Price Condition Element","sobjectName":"sbqq__pricecondition__c","replicateOwner":false,"replicateRecordType":false,"createMissing":true,"syncPicklistValues":true,"setAuditFields":false,"ignoreNamespace":false,"ignoreRelationshipConstraints":false,"active":true,"root":false,"allFields":true,"overrideRootSettings":false,"useLocalSchema":false,"customUpsertRecordHandling":"Standard Upsert","recordSelectionLimit":0,"bulkBatchSize":0,"dataSetFields":[{"id":"a181I00000123PhQAI","name":"SBQQ__Rule__c","externalId":true,"createMissing":false,"syncPicklistValues":false,"setEmpty":false,"scrambleValue":false,"fixedValue":false,"delayInsert":false,"deployLast":false,"copyRelationshipValue":false},{"id":"a181I00000123PiQAI","name":"SBQQ__Field__c","externalId":true,"createMissing":false,"syncPicklistValues":false,"setEmpty":false,"scrambleValue":false,"fixedValue":false,"delayInsert":false,"deployLast":false,"copyRelationshipValue":false},{"id":"a181I00000123PjQAI","name":"SBQQ__FilterType__c","externalId":true,"createMissing":false,"syncPicklistValues":false,"setEmpty":false,"scrambleValue":false,"fixedValue":false,"delayInsert":false,"deployLast":false,"copyRelationshipValue":false},{"id":"a181I00000123PkQAI","name":"SBQQ__Value__c","externalId":true,"createMissing":false,"syncPicklistValues":false,"setEmpty":false,"scrambleValue":false,"fixedValue":false,"delayInsert":false,"deployLast":false,"copyRelationshipValue":false},{"id":"a181I00000123PlQAI","name":"SBQQ__FilterVariable__c","externalId":true,"createMissing":false,"syncPicklistValues":false,"setEmpty":false,"scrambleValue":false,"fixedValue":false,"delayInsert":false,"deployLast":false,"copyRelationshipValue":false},{"id":"a181I00000123PmQAI","name":"SBQQ__Object__c","externalId":true,"createMissing":false,"syncPicklistValues":false,"setEmpty":false,"scrambleValue":false,"fixedValue":false,"delayInsert":false,"deployLast":false,"copyRelationshipValue":false},{"id":"a181I00000123PnQAI","name":"SBQQ__Operator__c","externalId":true,"createMissing":false,"syncPicklistValues":false,"setEmpty":false,"scrambleValue":false,"fixedValue":false,"delayInsert":false,"deployLast":false,"copyRelationshipValue":false},{"id":"a181I00000123PoQAI","name":"SBQQ__TestedVariable__c","externalId":true,"createMissing":false,"syncPicklistValues":false,"setEmpty":false,"scrambleValue":false,"fixedValue":false,"delayInsert":false,"deployLast":false,"copyRelationshipValue":false}],"relationships":[{"id":"a1G1I000000WFBCUA4","name":"SBQQ__TestedVariable__c","childDataSetId":"a171I0000017KtMQAU","parentDataSetId":"a171I0000017KtNQAU","isEnforceStrictQueryFilter":false,"isParentSelected":true,"isChildSelected":false},{"id":"a1G1I000000WFBBUA4","name":"SBQQ__FilterVariable__c","childDataSetId":"a171I0000017KtMQAU","parentDataSetId":"a171I0000017KtNQAU","isEnforceStrictQueryFilter":false,"isParentSelected":true,"isChildSelected":false},{"id":"a1G1I000000WFB9UAO","name":"SBQQ__FilterVariable__c","childDataSetId":"a171I0000017KtMQAU","parentDataSetId":"a171I0000017KtNQAU","isEnforceStrictQueryFilter":false,"isParentSelected":true,"isChildSelected":false},{"id":"a1G1I000000WFBAUA4","name":"SBQQ__TestedVariable__c","childDataSetId":"a171I0000017KtMQAU","parentDataSetId":"a171I0000017KtNQAU","isEnforceStrictQueryFilter":false,"isParentSelected":true,"isChildSelected":false}]},{"id":"a171I0000017KtNQAU","name":"Summary Variable Element","sobjectName":"sbqq__summaryvariable__c","replicateOwner":false,"replicateRecordType":false,"createMissing":true,"syncPicklistValues":true,"setAuditFields":false,"ignoreNamespace":false,"ignoreRelationshipConstraints":false,"active":true,"root":false,"allFields":true,"overrideRootSettings":false,"useLocalSchema":false,"customUpsertRecordHandling":"Standard Upsert","recordSelectionLimit":0,"bulkBatchSize":0,"dataSetFields":[{"id":"a181I00000123PpQAI","name":"Name","externalId":true,"createMissing":false,"syncPicklistValues":false,"setEmpty":false,"scrambleValue":false,"fixedValue":false,"delayInsert":false,"deployLast":false,"copyRelationshipValue":false}],"relationships":[{"id":"a1G1I000000WFBDUA4","name":"SBQQ__CombineWith__c","childDataSetId":"a171I0000017KtNQAU","parentDataSetId":"a171I0000017KtNQAU","isEnforceStrictQueryFilter":false,"isParentSelected":true,"isChildSelected":false}]},{"id":"a171I0000017KtOQAU","name":"Price Action Element","sobjectName":"sbqq__priceaction__c","replicateOwner":false,"replicateRecordType":false,"createMissing":true,"syncPicklistValues":true,"setAuditFields":false,"ignoreNamespace":false,"ignoreRelationshipConstraints":false,"active":true,"root":false,"allFields":true,"overrideRootSettings":false,"useLocalSchema":false,"customUpsertRecordHandling":"Standard Upsert","recordSelectionLimit":0,"bulkBatchSize":0,"dataSetFields":[{"id":"a181I00000123PqQAI","name":"SBQQ__Field__c","externalId":true,"createMissing":false,"syncPicklistValues":false,"setEmpty":false,"scrambleValue":false,"fixedValue":false,"delayInsert":false,"deployLast":false,"copyRelationshipValue":false},{"id":"a181I00000123PrQAI","name":"SBQQ__TargetObject__c","externalId":true,"createMissing":false,"syncPicklistValues":false,"setEmpty":false,"scrambleValue":false,"fixedValue":false,"delayInsert":false,"deployLast":false,"copyRelationshipValue":false},{"id":"a181I00000123PsQAI","name":"SBQQ__Value__c","externalId":true,"createMissing":false,"syncPicklistValues":false,"setEmpty":false,"scrambleValue":false,"fixedValue":false,"delayInsert":false,"deployLast":false,"copyRelationshipValue":false},{"id":"a181I00000123PtQAI","name":"SBQQ__Rule__c","externalId":true,"createMissing":false,"syncPicklistValues":false,"setEmpty":false,"scrambleValue":false,"fixedValue":false,"delayInsert":false,"deployLast":false,"copyRelationshipValue":false},{"id":"a181I00000123PuQAI","name":"SBQQ__Order__c","externalId":true,"createMissing":false,"syncPicklistValues":false,"setEmpty":false,"scrambleValue":false,"fixedValue":false,"delayInsert":false,"deployLast":false,"copyRelationshipValue":false},{"id":"a181I00000123PvQAI","name":"SBQQ__ValueField__c","externalId":true,"createMissing":false,"syncPicklistValues":false,"setEmpty":false,"scrambleValue":false,"fixedValue":false,"delayInsert":false,"deployLast":false,"copyRelationshipValue":false},{"id":"a181I00000123PwQAI","name":"SBQQ__SourceLookupField__c","externalId":true,"createMissing":false,"syncPicklistValues":false,"setEmpty":false,"scrambleValue":false,"fixedValue":false,"delayInsert":false,"deployLast":false,"copyRelationshipValue":false},{"id":"a181I00000123PxQAI","name":"SBQQ__SourceVariable__c","externalId":true,"createMissing":false,"syncPicklistValues":false,"setEmpty":false,"scrambleValue":false,"fixedValue":false,"delayInsert":false,"deployLast":false,"copyRelationshipValue":false}],"relationships":[{"id":"a1G1I000000WFBFUA4","name":"SBQQ__SourceVariable__c","childDataSetId":"a171I0000017KtOQAU","parentDataSetId":"a171I0000017KtNQAU","isEnforceStrictQueryFilter":false,"isParentSelected":true,"isChildSelected":false},{"id":"a1G1I000000WFBEUA4","name":"SBQQ__SourceVariable__c","childDataSetId":"a171I0000017KtOQAU","parentDataSetId":"a171I0000017KtNQAU","isEnforceStrictQueryFilter":false,"isParentSelected":true,"isChildSelected":false}]}]}